LICENSE
README.md
setup.cfg
setup.py
fast_bss_eval/__init__.py
fast_bss_eval.egg-info/PKG-INFO
fast_bss_eval.egg-info/SOURCES.txt
fast_bss_eval.egg-info/dependency_links.txt
fast_bss_eval.egg-info/requires.txt
fast_bss_eval.egg-info/top_level.txt
fast_bss_eval/numpy/__init__.py
fast_bss_eval/numpy/cgd.py
fast_bss_eval/numpy/helpers.py
fast_bss_eval/numpy/linalg.py
fast_bss_eval/numpy/metrics.py
fast_bss_eval/numpy/scale_invariant.py
fast_bss_eval/torch/__init__.py
fast_bss_eval/torch/cgd.py
fast_bss_eval/torch/compatibility.py
fast_bss_eval/torch/helpers.py
fast_bss_eval/torch/hungarian.py
fast_bss_eval/torch/linalg.py
fast_bss_eval/torch/metrics.py
fast_bss_eval/torch/scale_invariant.py