Metadata-Version: 2.1
Name: fast-bss-eval
Version: 0.1.4
Summary: Package for fast computation of BSS Eval metrics for source separation
Home-page: https://github.com/fakufaku/fast_bss_eval
Author: Robin Scheibler
Author-email: fakufaku@gmail.com
License: UNKNOWN
Project-URL: Bug Reports, https://github.com/fakufaku/fast_bss_eval/issues
Project-URL: Source, https://github.com/fakufaku/fast_bss_eval/
Platform: UNKNOWN
Classifier: Development Status :: 3 - Alpha
Classifier: Intended Audience :: Developers
Classifier: Topic :: Software Development :: Build Tools
Classifier: License :: OSI Approved :: MIT License
Classifier: Programming Language :: Python :: 3
Classifier: Programming Language :: Python :: 3.6
Classifier: Programming Language :: Python :: 3.7
Classifier: Programming Language :: Python :: 3.8
Classifier: Programming Language :: Python :: 3.9
Classifier: Programming Language :: Python :: 3 :: Only
Requires-Python: >=3.6, <4
Provides-Extra: all
